{
  "type": "FeatureCollection",
  "metadata": {
    "dataset": "bridge-pt",
    "section": "B",
    "count": 1,
    "tolerance_ft": 300.0,
    "source": "NPS GRSM ArcGIS Hub opendata"
  },
  "features": [
    {
      "type": "Feature",
      "properties": {
        "OBJECTID": 134,
        "NAME": "Clingmans Dome Road Bridge",
        "ROAD": "Clingmans Dome Access Road",
        "FACILITYTYPE": 1710,
        "FMSS_LOC": null,
        "BIPID": "5460-094",
        "DESCRIPTION": null,
        "API": null,
        "FCI": null,
        "CRV": null,
        "DM": null,
        "QTY": null,
        "UM": null,
        "STATUS": null,
        "HISTORICAL_STATUS": null,
        "OCCUPANT": null,
        "SITE": null,
        "BRDGLOAD": null,
        "BRDLOAD": null,
        "NATLDMRK": null,
        "OPSEAS": null,
        "PRIMUSE": null,
        "TOTAL_LENGTH": 6.0,
        "SPAN_LENGTH": 6.0,
        "DECK_WIDTH": 39.0,
        "CURB_TO_CURB_WIDTH": 35.5,
        "INVENTORY_RATING_H": 15,
        "INVENTORY_RATING_HS": 27,
        "INVENTORY_RATING_TYPE3": 35,
        "INVENTORY_RATING_TYPE3S2": 56,
        "INVENTORY_RATING_TYPE3_3": 60,
        "OPERATING_RATING_H": 25,
        "OPERATING_RATING_HS": 45,
        "OPERATING_RATING_TYPE3": 59,
        "OPERATING_RATING_TYPE3S2": 93,
        "OPERATING_RATING_TYPE3_3": 100,
        "NOTES": null,
        "ELEVATION": 5058,
        "X_COORD": 279872,
        "Y_COORD": 3943420,
        "LON": -83.43025409,
        "LAT": 35.61007239,
        "DATAACCESS": "Unrestricted",
        "MAPMETHOD": "Unknown",
        "SOURCEDATE": null,
        "XYACCURACY": "Unknown",
        "VALID_RESULT": "Raw",
        "GlobalID": "f420a670-4b06-40bc-b972-da341d4ec9b3",
        "_section": "B",
        "_sta_ft": 708.0,
        "_sta": "7+07.98",
        "_dist_from_alignment_ft": 106.0,
        "_reported_in": [
          "NPS-GIS",
          "RIP-C5",
          "RIP-C6"
        ],
        "_report_cross_refs": {
          "RIP-C5": {
            "pages_by_route": {
              "0010S": [
                8,
                9,
                10,
                11,
                13,
                15,
                17,
                25,
                26,
                27,
                51,
                52,
                57,
                63,
                87,
                117,
                118,
                119,
                120,
                143,
                144,
                145,
                146,
                164,
                165,
                166,
                167,
                255,
                260,
                261,
                262,
                263,
                264,
                265,
                266,
                267,
                268,
                313
              ]
            }
          },
          "RIP-C6": {
            "pages_by_route": {
              "0010S": [
                8,
                9,
                11,
                13,
                14,
                17,
                28,
                29,
                30,
                50,
                55,
                56,
                63,
                71,
                72,
                89,
                124,
                125,
                126,
                127,
                147,
                148,
                149,
                150,
                355,
                356,
                357,
                358,
                359,
                360,
                361,
                362,
                363,
                364,
                365,
                366,
                367,
                368,
                369,
                370,
                371,
                372,
                374,
                375,
                376,
                546,
                644,
                662,
                663,
                664,
                674,
                685,
                686,
                691,
                692,
                703
              ]
            }
          }
        }
      },
      "geometry": {
        "type": "Point",
        "coordinates": [
          -83.430258122789,
          35.6100792505261
        ]
      }
    }
  ]
}