{
  "type": "FeatureCollection",
  "metadata": {
    "dataset": "gates",
    "section": "B",
    "count": 1,
    "tolerance_ft": 300.0,
    "source": "NPS GRSM ArcGIS Hub opendata"
  },
  "features": [
    {
      "type": "Feature",
      "properties": {
        "OBJECTID": 139,
        "LOC_NAME": null,
        "KEY_": null,
        "CLOSURE": null,
        "NOTES": null,
        "FMSS_LOC": null,
        "FMSS_ASSET": null,
        "ROAD": "Clingmans Dome Access Road",
        "TRAIL": "Appalachian Trail",
        "ELEVATION": 5048,
        "X_COORD": 280064,
        "Y_COORD": 3943519,
        "LON": -83.42816589,
        "LAT": 35.61100375,
        "DMSLAT": "35 36 39.63820969N",
        "DMSLON": "083 25 41.41170563W",
        "DDMLAT": "35 36.66063683N",
        "DDMLON": "083 25.69019509W",
        "DATAACCESS": "Unrestricted",
        "MAPMETHOD": "Unknown",
        "SOURCEDATE": null,
        "XYACCURACY": ">=1m and <5m",
        "VALID_RESULT": "Certified",
        "GlobalID": "bd1608eb-d268-4f9d-ad9f-4beb99f8fcc7",
        "_section": "B",
        "_sta_ft": 0.0,
        "_sta": "0+00.00",
        "_dist_from_alignment_ft": 115.0,
        "_reported_in": [
          "NPS-GIS",
          "RIP-C5",
          "RIP-C6"
        ],
        "_report_cross_refs": {
          "RIP-C5": {
            "pages_by_route": {
              "0010S": [
                8,
                9,
                10,
                11,
                13,
                15,
                17,
                25,
                26,
                27,
                51,
                52,
                57,
                63,
                87,
                117,
                118,
                119,
                120,
                143,
                144,
                145,
                146,
                164,
                165,
                166,
                167,
                255,
                260,
                261,
                262,
                263,
                264,
                265,
                266,
                267,
                268,
                313
              ]
            }
          },
          "RIP-C6": {
            "pages_by_route": {
              "0010S": [
                8,
                9,
                11,
                13,
                14,
                17,
                28,
                29,
                30,
                50,
                55,
                56,
                63,
                71,
                72,
                89,
                124,
                125,
                126,
                127,
                147,
                148,
                149,
                150,
                355,
                356,
                357,
                358,
                359,
                360,
                361,
                362,
                363,
                364,
                365,
                366,
                367,
                368,
                369,
                370,
                371,
                372,
                374,
                375,
                376,
                546,
                644,
                662,
                663,
                664,
                674,
                685,
                686,
                691,
                692,
                703
              ]
            }
          }
        }
      },
      "geometry": {
        "type": "Point",
        "coordinates": [
          -83.4281699142318,
          35.611010616802
        ]
      }
    }
  ]
}